{
    "1185330189": {
        "reminders": [
            {
                "name": "Дима",
                "birthday": "01.01.1999",
                "intervals": [
                    1,
                    7,
                    30
                ]
            },
            {
                "name": "Сергей Вавилин",
                "birthday": "22.03.2005",
                "intervals": [
                    1,
                    7,
                    30
                ]
            },
            {
                "name": "Полина",
                "birthday": "05.07.2010",
                "intervals": [
                    1,
                    7,
                    10
                ]
            }
        ]
    }
}